{
    "Loaded": true,
    "Name": "Kinging Farmstead",
    "RegionName": "Alcaire",
    "HasDungeon": false,
    "MapTableData": {
        "MapId": 127718,
        "Latitude": 47616,
        "Longitude": 91904,
        "LocationType": 3,
        "DungeonType": 255,
        "Discovered": false,
        "Key": 0,
        "LocationId": 1150
    },
    "Exterior": {
        "RecordElement": {
            "Header": {
                "X": 23541760,
                "Y": 4175873,
                "IsExterior": 32768,
                "Unknown2": 0,
                "LocationId": 1150,
                "IsInterior": 0,
                "ExteriorLocationId": 1150,
                "LocationName": "Kinging Farmstead"
            }
        },
        "BuildingCount": 32,
        "Buildings": [
            {
                "NameSeed": 29586,
                "FactionId": 0,
                "Sector": 0,
                "LocationId": 0,
                "BuildingType": 18,
                "Quality": 17
            },
            {
                "NameSeed": 8606,
                "FactionId": 0,
                "Sector": 0,
                "LocationId": 0,
                "BuildingType": 18,
                "Quality": 10
            },
            {
                "NameSeed": 40367,
                "FactionId": 0,
                "Sector": 0,
                "LocationId": 0,
                "BuildingType": 19,
                "Quality": 12
            },
            {
                "NameSeed": 25018,
                "FactionId": 0,
                "Sector": 0,
                "LocationId": 0,
                "BuildingType": 18,
                "Quality": 11
            },
            {
                "NameSeed": 18520,
                "FactionId": 0,
                "Sector": 0,
                "LocationId": 0,
                "BuildingType": 18,
                "Quality": 7
            },
            {
                "NameSeed": 51816,
                "FactionId": 0,
                "Sector": 0,
                "LocationId": 0,
                "BuildingType": 19,
                "Quality": 15
            },
            {
                "NameSeed": 43766,
                "FactionId": 0,
                "Sector": 0,
                "LocationId": 0,
                "BuildingType": 18,
                "Quality": 17
            },
            {
                "NameSeed": 13348,
                "FactionId": 0,
                "Sector": 0,
                "LocationId": 0,
                "BuildingType": 18,
                "Quality": 19
            },
            {
                "NameSeed": 14441,
                "FactionId": 0,
                "Sector": 0,
                "LocationId": 0,
                "BuildingType": 18,
                "Quality": 13
            },
            {
                "NameSeed": 9671,
                "FactionId": 0,
                "Sector": 0,
                "LocationId": 0,
                "BuildingType": 19,
                "Quality": 7
            },
            {
                "NameSeed": 26993,
                "FactionId": 0,
                "Sector": 0,
                "LocationId": 0,
                "BuildingType": 18,
                "Quality": 9
            },
            {
                "NameSeed": 41688,
                "FactionId": 0,
                "Sector": 0,
                "LocationId": 0,
                "BuildingType": 19,
                "Quality": 18
            },
            {
                "NameSeed": 50966,
                "FactionId": 0,
                "Sector": 0,
                "LocationId": 0,
                "BuildingType": 19,
                "Quality": 14
            },
            {
                "NameSeed": 10052,
                "FactionId": 0,
                "Sector": 0,
                "LocationId": 0,
                "BuildingType": 18,
                "Quality": 19
            },
            {
                "NameSeed": 51588,
                "FactionId": 0,
                "Sector": 0,
                "LocationId": 0,
                "BuildingType": 19,
                "Quality": 6
            },
            {
                "NameSeed": 594,
                "FactionId": 0,
                "Sector": 0,
                "LocationId": 0,
                "BuildingType": 18,
                "Quality": 10
            },
            {
                "NameSeed": 18888,
                "FactionId": 0,
                "Sector": 0,
                "LocationId": 0,
                "BuildingType": 18,
                "Quality": 2
            },
            {
                "NameSeed": 41568,
                "FactionId": 0,
                "Sector": 0,
                "LocationId": 0,
                "BuildingType": 18,
                "Quality": 6
            },
            {
                "NameSeed": 39576,
                "FactionId": 0,
                "Sector": 0,
                "LocationId": 0,
                "BuildingType": 18,
                "Quality": 2
            },
            {
                "NameSeed": 29736,
                "FactionId": 0,
                "Sector": 0,
                "LocationId": 0,
                "BuildingType": 18,
                "Quality": 5
            },
            {
                "NameSeed": 53130,
                "FactionId": 0,
                "Sector": 0,
                "LocationId": 0,
                "BuildingType": 18,
                "Quality": 18
            },
            {
                "NameSeed": 33618,
                "FactionId": 0,
                "Sector": 0,
                "LocationId": 0,
                "BuildingType": 18,
                "Quality": 17
            },
            {
                "NameSeed": 38447,
                "FactionId": 0,
                "Sector": 0,
                "LocationId": 0,
                "BuildingType": 18,
                "Quality": 5
            },
            {
                "NameSeed": 32719,
                "FactionId": 0,
                "Sector": 0,
                "LocationId": 0,
                "BuildingType": 18,
                "Quality": 6
            },
            {
                "NameSeed": 64488,
                "FactionId": 0,
                "Sector": 0,
                "LocationId": 0,
                "BuildingType": 18,
                "Quality": 1
            },
            {
                "NameSeed": 31789,
                "FactionId": 0,
                "Sector": 0,
                "LocationId": 0,
                "BuildingType": 19,
                "Quality": 10
            },
            {
                "NameSeed": 30903,
                "FactionId": 0,
                "Sector": 0,
                "LocationId": 0,
                "BuildingType": 19,
                "Quality": 10
            },
            {
                "NameSeed": 9834,
                "FactionId": 0,
                "Sector": 0,
                "LocationId": 0,
                "BuildingType": 18,
                "Quality": 16
            },
            {
                "NameSeed": 27407,
                "FactionId": 0,
                "Sector": 0,
                "LocationId": 0,
                "BuildingType": 21,
                "Quality": 2
            },
            {
                "NameSeed": 131,
                "FactionId": 0,
                "Sector": 0,
                "LocationId": 0,
                "BuildingType": 21,
                "Quality": 5
            },
            {
                "NameSeed": 42910,
                "FactionId": 0,
                "Sector": 0,
                "LocationId": 0,
                "BuildingType": 21,
                "Quality": 7
            },
            {
                "NameSeed": 64816,
                "FactionId": 0,
                "Sector": 0,
                "LocationId": 0,
                "BuildingType": 21,
                "Quality": 17
            }
        ],
        "ExteriorData": {
            "AnotherName": "Kinging Farmstead",
            "MapId": 127718,
            "LocationId": 1150,
            "Width": 1,
            "Height": 1,
            "PortTownAndUnknown": 0,
            "BlockNames": [
                "FARMAA05.RMB"
            ]
        }
    },
    "Dungeon": {
        "RecordElement": {
            "Header": {
                "X": 0,
                "Y": 0,
                "IsExterior": 0,
                "Unknown2": 0,
                "LocationId": 0,
                "IsInterior": 0,
                "ExteriorLocationId": 0,
                "LocationName": null
            }
        },
        "Header": {
            "BlockCount": 0
        },
        "Blocks": null
    },
    "Climate": {
        "WorldClimate": 224,
        "ClimateType": 0,
        "NatureSet": 503,
        "GroundArchive": 2,
        "NatureArchive": 503,
        "SkyBase": 8,
        "People": 2,
        "Names": 0
    },
    "Politic": 34,
    "RegionIndex": 162,
    "LocationIndex": 0
}