{"Loaded":true,"Name":"The Shujon Farmstead","RegionName":"Totambu","HasDungeon":false,"MapTableData":{"MapId":373923,"Latitude":16128,"Longitude":118144,"LocationType":3,"DungeonType":255,"Discovered":false,"Key":0,"LocationId":9746},"Exterior":{"RecordElement":{"Header":{"X":30255104,"Y":12232705,"IsExterior":32768,"Unknown2":0,"LocationId":9746,"IsInterior":0,"ExteriorLocationId":9746,"LocationName":"The Shujon Farmstead"}},"BuildingCount":288,"Buildings":[{"NameSeed":43284,"FactionId":0,"Sector":0,"LocationId":0,"BuildingType":17,"Quality":19},{"NameSeed":41587,"FactionId":0,"Sector":0,"LocationId":0,"BuildingType":18,"Quality":12},{"NameSeed":17103,"FactionId":0,"Sector":0,"LocationId":0,"BuildingType":19,"Quality":17},{"NameSeed":58112,"FactionId":0,"Sector":0,"LocationId":0,"BuildingType":18,"Quality":9},{"NameSeed":14880,"FactionId":0,"Sector":0,"LocationId":0,"BuildingType":18,"Quality":16},{"NameSeed":41482,"FactionId":0,"Sector":0,"LocationId":0,"BuildingType":18,"Quality":7},{"NameSeed":21147,"FactionId":0,"Sector":0,"LocationId":0,"BuildingType":15,"Quality":16},{"NameSeed":62258,"FactionId":0,"Sector":0,"LocationId":0,"BuildingType":18,"Quality":11},{"NameSeed":1557,"FactionId":0,"Sector":0,"LocationId":0,"BuildingType":18,"Quality":7},{"NameSeed":63728,"FactionId":0,"Sector":0,"LocationId":0,"BuildingType":18,"Quality":6},{"NameSeed":61186,"FactionId":0,"Sector":0,"LocationId":0,"BuildingType":18,"Quality":13},{"NameSeed":60606,"FactionId":0,"Sector":0,"LocationId":0,"BuildingType":18,"Quality":2},{"NameSeed":22708,"FactionId":0,"Sector":0,"LocationId":0,"BuildingType":19,"Quality":8},{"NameSeed":46255,"FactionId":0,"Sector":0,"LocationId":0,"BuildingType":18,"Quality":2},{"NameSeed":24327,"FactionId":0,"Sector":0,"LocationId":0,"BuildingType":18,"Quality":12},{"NameSeed":19298,"FactionId":0,"Sector":0,"LocationId":0,"BuildingType":18,"Quality":1},{"NameSeed":3039,"FactionId":0,"Sector":0,"LocationId":0,"BuildingType":18,"Quality":1},{"NameSeed":49883,"FactionId":0,"Sector":0,"LocationId":0,"BuildingType":18,"Quality":2},{"NameSeed":49429,"FactionId":0,"Sector":0,"LocationId":0,"BuildingType":18,"Quality":1},{"NameSeed":22034,"FactionId":0,"Sector":0,"LocationId":0,"BuildingType":18,"Quality":19},{"NameSeed":37719,"FactionId":0,"Sector":0,"LocationId":0,"BuildingType":18,"Quality":17},{"NameSeed":29804,"FactionId":0,"Sector":0,"LocationId":0,"BuildingType":18,"Quality":18},{"NameSeed":57221,"FactionId":0,"Sector":0,"LocationId":0,"BuildingType":18,"Quality":12},{"NameSeed":41471,"FactionId":0,"Sector":0,"LocationId":0,"BuildingType":18,"Quality":9},{"NameSeed":16428,"FactionId":0,"Sector":0,"LocationId":0,"BuildingType":18,"Quality":9},{"NameSeed":36619,"FactionId":0,"Sector":0,"LocationId":0,"BuildingType":19,"Quality":3},{"NameSeed":25569,"FactionId":0,"Sector":0,"LocationId":0,"BuildingType":19,"Quality":15},{"NameSeed":15893,"FactionId":0,"Sector":0,"LocationId":0,"BuildingType":18,"Quality":12},{"NameSeed":6921,"FactionId":0,"Sector":0,"LocationId":0,"BuildingType":21,"Quality":1},{"NameSeed":47701,"FactionId":0,"Sector":0,"LocationId":0,"BuildingType":21,"Quality":19},{"NameSeed":42447,"FactionId":0,"Sector":0,"LocationId":0,"BuildingType":21,"Quality":4},{"NameSeed":41865,"FactionId":0,"Sector":0,"LocationId":0,"BuildingType":21,"Quality":5},{"NameSeed":58618,"FactionId":0,"Sector":0,"LocationId":0,"BuildingType":18,"Quality":16},{"NameSeed":42709,"FactionId":0,"Sector":0,"LocationId":0,"BuildingType":15,"Quality":13},{"NameSeed":3357,"FactionId":0,"Sector":0,"LocationId":0,"BuildingType":19,"Quality":19},{"NameSeed":8985,"FactionId":0,"Sector":0,"LocationId":0,"BuildingType":18,"Quality":6},{"NameSeed":34585,"FactionId":0,"Sector":0,"LocationId":0,"BuildingType":18,"Quality":20},{"NameSeed":17975,"FactionId":0,"Sector":0,"LocationId":0,"BuildingType":18,"Quality":1},{"NameSeed":16088,"FactionId":0,"Sector":0,"LocationId":0,"BuildingType":18,"Quality":15},{"NameSeed":14186,"FactionId":0,"Sector":0,"LocationId":0,"BuildingType":19,"Quality":6},{"NameSeed":25600,"FactionId":0,"Sector":0,"LocationId":0,"BuildingType":18,"Quality":11},{"NameSeed":29472,"FactionId":0,"Sector":0,"LocationId":0,"BuildingType":18,"Quality":5},{"NameSeed":39537,"FactionId":0,"Sector":0,"LocationId":0,"BuildingType":18,"Quality":8},{"NameSeed":55554,"FactionId":0,"Sector":0,"LocationId":0,"BuildingType":18,"Quality":5},{"NameSeed":63695,"FactionId":0,"Sector":0,"LocationId":0,"BuildingType":18,"Quality":10},{"NameSeed":60298,"FactionId":0,"Sector":0,"LocationId":0,"BuildingType":18,"Quality":9},{"NameSeed":18983,"FactionId":0,"Sector":0,"LocationId":0,"BuildingType":18,"Quality":8},{"NameSeed":25699,"FactionId":0,"Sector":0,"LocationId":0,"BuildingType":18,"Quality":16},{"NameSeed":55885,"FactionId":0,"Sector":0,"LocationId":0,"BuildingType":18,"Quality":4},{"NameSeed":56275,"FactionId":0,"Sector":0,"LocationId":0,"BuildingType":18,"Quality":11},{"NameSeed":4795,"FactionId":0,"Sector":0,"LocationId":0,"BuildingType":18,"Quality":11},{"NameSeed":3522,"FactionId":0,"Sector":0,"LocationId":0,"BuildingType":18,"Quality":4},{"NameSeed":47982,"FactionId":0,"Sector":0,"LocationId":0,"BuildingType":18,"Quality":17},{"NameSeed":56796,"FactionId":0,"Sector":0,"LocationId":0,"BuildingType":18,"Quality":11},{"NameSeed":31311,"FactionId":0,"Sector":0,"LocationId":0,"BuildingType":18,"Quality":14},{"NameSeed":1867,"FactionId":0,"Sector":0,"LocationId":0,"BuildingType":18,"Quality":11},{"NameSeed":45478,"FactionId":0,"Sector":0,"LocationId":0,"BuildingType":18,"Quality":9},{"NameSeed":18671,"FactionId":0,"Sector":0,"LocationId":0,"BuildingType":19,"Quality":12},{"NameSeed":28738,"FactionId":0,"Sector":0,"LocationId":0,"BuildingType":19,"Quality":15},{"NameSeed":54643,"FactionId":0,"Sector":0,"LocationId":0,"BuildingType":18,"Quality":13},{"NameSeed":23853,"FactionId":0,"Sector":0,"LocationId":0,"BuildingType":21,"Quality":4},{"NameSeed":57125,"FactionId":0,"Sector":0,"LocationId":0,"BuildingType":21,"Quality":10},{"NameSeed":49039,"FactionId":0,"Sector":0,"LocationId":0,"BuildingType":21,"Quality":9},{"NameSeed":47233,"FactionId":0,"Sector":0,"LocationId":0,"BuildingType":21,"Quality":1},{"NameSeed":51485,"FactionId":0,"Sector":0,"LocationId":0,"BuildingType":18,"Quality":1},{"NameSeed":4099,"FactionId":0,"Sector":0,"LocationId":0,"BuildingType":18,"Quality":19},{"NameSeed":46475,"FactionId":0,"Sector":0,"LocationId":0,"BuildingType":18,"Quality":1},{"NameSeed":9552,"FactionId":0,"Sector":0,"LocationId":0,"BuildingType":18,"Quality":2},{"NameSeed":29052,"FactionId":0,"Sector":0,"LocationId":0,"BuildingType":18,"Quality":11},{"NameSeed":1393,"FactionId":0,"Sector":0,"LocationId":0,"BuildingType":18,"Quality":15},{"NameSeed":26305,"FactionId":0,"Sector":0,"LocationId":0,"BuildingType":18,"Quality":12},{"NameSeed":28823,"FactionId":0,"Sector":0,"LocationId":0,"BuildingType":18,"Quality":18},{"NameSeed":21238,"FactionId":0,"Sector":0,"LocationId":0,"BuildingType":18,"Quality":1},{"NameSeed":49358,"FactionId":0,"Sector":0,"LocationId":0,"BuildingType":18,"Quality":6},{"NameSeed":10458,"FactionId":0,"Sector":0,"LocationId":0,"BuildingType":18,"Quality":7},{"NameSeed":59842,"FactionId":0,"Sector":0,"LocationId":0,"BuildingType":18,"Quality":14},{"NameSeed":64585,"FactionId":0,"Sector":0,"LocationId":0,"BuildingType":18,"Quality":17},{"NameSeed":34226,"FactionId":0,"Sector":0,"LocationId":0,"BuildingType":18,"Quality":6},{"NameSeed":22556,"FactionId":0,"Sector":0,"LocationId":0,"BuildingType":18,"Quality":13},{"NameSeed":21812,"FactionId":0,"Sector":0,"LocationId":0,"BuildingType":18,"Quality":8},{"NameSeed":2229,"FactionId":0,"Sector":0,"LocationId":0,"BuildingType":18,"Quality":15},{"NameSeed":16849,"FactionId":0,"Sector":0,"LocationId":0,"BuildingType":18,"Quality":8},{"NameSeed":37346,"FactionId":0,"Sector":0,"LocationId":0,"BuildingType":18,"Quality":6},{"NameSeed":33949,"FactionId":0,"Sector":0,"LocationId":0,"BuildingType":18,"Quality":3},{"NameSeed":40634,"FactionId":0,"Sector":0,"LocationId":0,"BuildingType":18,"Quality":4},{"NameSeed":36274,"FactionId":0,"Sector":0,"LocationId":0,"BuildingType":18,"Quality":7},{"NameSeed":54381,"FactionId":0,"Sector":0,"LocationId":0,"BuildingType":18,"Quality":7},{"NameSeed":63614,"FactionId":0,"Sector":0,"LocationId":0,"BuildingType":18,"Quality":4},{"NameSeed":46780,"FactionId":0,"Sector":0,"LocationId":0,"BuildingType":18,"Quality":7},{"NameSeed":58494,"FactionId":0,"Sector":0,"LocationId":0,"BuildingType":19,"Quality":18},{"NameSeed":4071,"FactionId":0,"Sector":0,"LocationId":0,"BuildingType":19,"Quality":11},{"NameSeed":63709,"FactionId":0,"Sector":0,"LocationId":0,"BuildingType":18,"Quality":13},{"NameSeed":51740,"FactionId":0,"Sector":0,"LocationId":0,"BuildingType":21,"Quality":7},{"NameSeed":14155,"FactionId":0,"Sector":0,"LocationId":0,"BuildingType":21,"Quality":8},{"NameSeed":56040,"FactionId":0,"Sector":0,"LocationId":0,"BuildingType":21,"Quality":13},{"NameSeed":47302,"FactionId":0,"Sector":0,"LocationId":0,"BuildingType":21,"Quality":19},{"NameSeed":44738,"FactionId":0,"Sector":0,"LocationId":0,"BuildingType":21,"Quality":8},{"NameSeed":41705,"FactionId":0,"Sector":0,"LocationId":0,"BuildingType":21,"Quality":12},{"NameSeed":38528,"FactionId":0,"Sector":0,"LocationId":0,"BuildingType":21,"Quality":16},{"NameSeed":61526,"FactionId":0,"Sector":0,"LocationId":0,"BuildingType":21,"Quality":6},{"NameSeed":48469,"FactionId":0,"Sector":0,"LocationId":0,"BuildingType":21,"Quality":4},{"NameSeed":50131,"FactionId":0,"Sector":0,"LocationId":0,"BuildingType":21,"Quality":11},{"NameSeed":37627,"FactionId":0,"Sector":0,"LocationId":0,"BuildingType":18,"Quality":2},{"NameSeed":11789,"FactionId":0,"Sector":0,"LocationId":0,"BuildingType":18,"Quality":19},{"NameSeed":1160,"FactionId":0,"Sector":0,"LocationId":0,"BuildingType":18,"Quality":2},{"NameSeed":5782,"FactionId":0,"Sector":0,"LocationId":0,"BuildingType":18,"Quality":14},{"NameSeed":36045,"FactionId":0,"Sector":0,"LocationId":0,"BuildingType":18,"Quality":13},{"NameSeed":9873,"FactionId":0,"Sector":0,"LocationId":0,"BuildingType":18,"Quality":1},{"NameSeed":25527,"FactionId":0,"Sector":0,"LocationId":0,"BuildingType":18,"Quality":17},{"NameSeed":30369,"FactionId":0,"Sector":0,"LocationId":0,"BuildingType":18,"Quality":6},{"NameSeed":55171,"FactionId":236,"Sector":0,"LocationId":0,"BuildingType":2,"Quality":7},{"NameSeed":55844,"FactionId":0,"Sector":0,"LocationId":0,"BuildingType":18,"Quality":11},{"NameSeed":21492,"FactionId":0,"Sector":0,"LocationId":0,"BuildingType":18,"Quality":12},{"NameSeed":2244,"FactionId":0,"Sector":0,"LocationId":0,"BuildingType":18,"Quality":13},{"NameSeed":27761,"FactionId":0,"Sector":0,"LocationId":0,"BuildingType":18,"Quality":7},{"NameSeed":15358,"FactionId":510,"Sector":0,"LocationId":0,"BuildingType":6,"Quality":3},{"NameSeed":4834,"FactionId":0,"Sector":0,"LocationId":0,"BuildingType":18,"Quality":14},{"NameSeed":8842,"FactionId":0,"Sector":0,"LocationId":0,"BuildingType":19,"Quality":19},{"NameSeed":47123,"FactionId":0,"Sector":0,"LocationId":0,"BuildingType":19,"Quality":4},{"NameSeed":12020,"FactionId":0,"Sector":0,"LocationId":0,"BuildingType":18,"Quality":17},{"NameSeed":19234,"FactionId":0,"Sector":0,"LocationId":0,"BuildingType":18,"Quality":20},{"NameSeed":7374,"FactionId":0,"Sector":0,"LocationId":0,"BuildingType":18,"Quality":7},{"NameSeed":55150,"FactionId":0,"Sector":0,"LocationId":0,"BuildingType":18,"Quality":17},{"NameSeed":892,"FactionId":0,"Sector":0,"LocationId":0,"BuildingType":18,"Quality":20},{"NameSeed":42466,"FactionId":0,"Sector":0,"LocationId":0,"BuildingType":18,"Quality":18},{"NameSeed":36208,"FactionId":0,"Sector":0,"LocationId":0,"BuildingType":18,"Quality":9},{"NameSeed":37912,"FactionId":0,"Sector":0,"LocationId":0,"BuildingType":18,"Quality":10},{"NameSeed":39325,"FactionId":0,"Sector":0,"LocationId":0,"BuildingType":0,"Quality":20},{"NameSeed":38430,"FactionId":0,"Sector":0,"LocationId":0,"BuildingType":17,"Quality":14},{"NameSeed":38021,"FactionId":0,"Sector":0,"LocationId":0,"BuildingType":18,"Quality":11},{"NameSeed":33713,"FactionId":0,"Sector":0,"LocationId":0,"BuildingType":19,"Quality":7},{"NameSeed":36169,"FactionId":0,"Sector":0,"LocationId":0,"BuildingType":18,"Quality":20},{"NameSeed":48539,"FactionId":0,"Sector":0,"LocationId":0,"BuildingType":18,"Quality":10},{"NameSeed":61514,"FactionId":0,"Sector":0,"LocationId":0,"BuildingType":18,"Quality":2},{"NameSeed":16138,"FactionId":0,"Sector":0,"LocationId":0,"BuildingType":15,"Quality":17},{"NameSeed":24001,"FactionId":0,"Sector":0,"LocationId":0,"BuildingType":18,"Quality":12},{"NameSeed":34408,"FactionId":0,"Sector":0,"LocationId":0,"BuildingType":18,"Quality":2},{"NameSeed":57818,"FactionId":0,"Sector":0,"LocationId":0,"BuildingType":18,"Quality":19},{"NameSeed":63088,"FactionId":0,"Sector":0,"LocationId":0,"BuildingType":18,"Quality":12},{"NameSeed":31895,"FactionId":0,"Sector":0,"LocationId":0,"BuildingType":18,"Quality":9},{"NameSeed":65178,"FactionId":0,"Sector":0,"LocationId":0,"BuildingType":19,"Quality":3},{"NameSeed":17776,"FactionId":0,"Sector":0,"LocationId":0,"BuildingType":18,"Quality":9},{"NameSeed":37443,"FactionId":0,"Sector":0,"LocationId":0,"BuildingType":18,"Quality":13},{"NameSeed":50627,"FactionId":0,"Sector":0,"LocationId":0,"BuildingType":18,"Quality":14},{"NameSeed":50427,"FactionId":0,"Sector":0,"LocationId":0,"BuildingType":18,"Quality":5},{"NameSeed":48478,"FactionId":0,"Sector":0,"LocationId":0,"BuildingType":18,"Quality":7},{"NameSeed":36301,"FactionId":0,"Sector":0,"LocationId":0,"BuildingType":18,"Quality":16},{"NameSeed":29663,"FactionId":0,"Sector":0,"LocationId":0,"BuildingType":18,"Quality":15},{"NameSeed":55287,"FactionId":0,"Sector":0,"LocationId":0,"BuildingType":18,"Quality":5},{"NameSeed":49093,"FactionId":0,"Sector":0,"LocationId":0,"BuildingType":18,"Quality":4},{"NameSeed":39826,"FactionId":0,"Sector":0,"LocationId":0,"BuildingType":18,"Quality":1},{"NameSeed":24102,"FactionId":0,"Sector":0,"LocationId":0,"BuildingType":18,"Quality":12},{"NameSeed":14739,"FactionId":0,"Sector":0,"LocationId":0,"BuildingType":18,"Quality":5},{"NameSeed":15179,"FactionId":0,"Sector":0,"LocationId":0,"BuildingType":19,"Quality":2},{"NameSeed":1854,"FactionId":0,"Sector":0,"LocationId":0,"BuildingType":19,"Quality":10},{"NameSeed":4172,"FactionId":0,"Sector":0,"LocationId":0,"BuildingType":18,"Quality":18},{"NameSeed":21575,"FactionId":0,"Sector":0,"LocationId":0,"BuildingType":21,"Quality":20},{"NameSeed":10340,"FactionId":0,"Sector":0,"LocationId":0,"BuildingType":21,"Quality":16},{"NameSeed":17252,"FactionId":0,"Sector":0,"LocationId":0,"BuildingType":21,"Quality":5},{"NameSeed":8352,"FactionId":0,"Sector":0,"LocationId":0,"BuildingType":21,"Quality":9},{"NameSeed":61215,"FactionId":0,"Sector":0,"LocationId":0,"BuildingType":18,"Quality":16},{"NameSeed":20236,"FactionId":0,"Sector":0,"LocationId":0,"BuildingType":15,"Quality":6},{"NameSeed":7800,"FactionId":0,"Sector":0,"LocationId":0,"BuildingType":19,"Quality":8},{"NameSeed":54141,"FactionId":0,"Sector":0,"LocationId":0,"BuildingType":18,"Quality":2},{"NameSeed":35527,"FactionId":0,"Sector":0,"LocationId":0,"BuildingType":18,"Quality":20},{"NameSeed":25395,"FactionId":0,"Sector":0,"LocationId":0,"BuildingType":18,"Quality":9},{"NameSeed":40224,"FactionId":0,"Sector":0,"LocationId":0,"BuildingType":18,"Quality":9},{"NameSeed":12971,"FactionId":0,"Sector":0,"LocationId":0,"BuildingType":19,"Quality":8},{"NameSeed":62002,"FactionId":0,"Sector":0,"LocationId":0,"BuildingType":18,"Quality":3},{"NameSeed":37145,"FactionId":0,"Sector":0,"LocationId":0,"BuildingType":18,"Quality":3},{"NameSeed":63934,"FactionId":0,"Sector":0,"LocationId":0,"BuildingType":18,"Quality":9},{"NameSeed":12032,"FactionId":0,"Sector":0,"LocationId":0,"BuildingType":18,"Quality":12},{"NameSeed":10321,"FactionId":0,"Sector":0,"LocationId":0,"BuildingType":18,"Quality":4},{"NameSeed":18749,"FactionId":0,"Sector":0,"LocationId":0,"BuildingType":18,"Quality":14},{"NameSeed":36049,"FactionId":0,"Sector":0,"LocationId":0,"BuildingType":18,"Quality":18},{"NameSeed":46946,"FactionId":0,"Sector":0,"LocationId":0,"BuildingType":18,"Quality":3},{"NameSeed":9502,"FactionId":0,"Sector":0,"LocationId":0,"BuildingType":18,"Quality":6},{"NameSeed":3171,"FactionId":0,"Sector":0,"LocationId":0,"BuildingType":18,"Quality":18},{"NameSeed":59277,"FactionId":0,"Sector":0,"LocationId":0,"BuildingType":18,"Quality":4},{"NameSeed":55488,"FactionId":0,"Sector":0,"LocationId":0,"BuildingType":18,"Quality":17},{"NameSeed":29941,"FactionId":0,"Sector":0,"LocationId":0,"BuildingType":18,"Quality":19},{"NameSeed":58544,"FactionId":0,"Sector":0,"LocationId":0,"BuildingType":18,"Quality":7},{"NameSeed":62278,"FactionId":0,"Sector":0,"LocationId":0,"BuildingType":18,"Quality":20},{"NameSeed":27082,"FactionId":0,"Sector":0,"LocationId":0,"BuildingType":18,"Quality":16},{"NameSeed":50286,"FactionId":0,"Sector":0,"LocationId":0,"BuildingType":18,"Quality":1},{"NameSeed":1571,"FactionId":0,"Sector":0,"LocationId":0,"BuildingType":19,"Quality":14},{"NameSeed":24609,"FactionId":0,"Sector":0,"LocationId":0,"BuildingType":19,"Quality":17},{"NameSeed":62194,"FactionId":0,"Sector":0,"LocationId":0,"BuildingType":18,"Quality":11},{"NameSeed":31864,"FactionId":0,"Sector":0,"LocationId":0,"BuildingType":21,"Quality":10},{"NameSeed":47913,"FactionId":0,"Sector":0,"LocationId":0,"BuildingType":21,"Quality":9},{"NameSeed":21845,"FactionId":0,"Sector":0,"LocationId":0,"BuildingType":21,"Quality":2},{"NameSeed":27444,"FactionId":0,"Sector":0,"LocationId":0,"BuildingType":21,"Quality":4},{"NameSeed":26834,"FactionId":0,"Sector":0,"LocationId":0,"BuildingType":18,"Quality":17},{"NameSeed":5672,"FactionId":0,"Sector":0,"LocationId":0,"BuildingType":15,"Quality":12},{"NameSeed":24960,"FactionId":0,"Sector":0,"LocationId":0,"BuildingType":19,"Quality":8},{"NameSeed":43708,"FactionId":0,"Sector":0,"LocationId":0,"BuildingType":18,"Quality":13},{"NameSeed":18347,"FactionId":0,"Sector":0,"LocationId":0,"BuildingType":18,"Quality":13},{"NameSeed":1118,"FactionId":0,"Sector":0,"LocationId":0,"BuildingType":18,"Quality":14},{"NameSeed":37948,"FactionId":0,"Sector":0,"LocationId":0,"BuildingType":18,"Quality":13},{"NameSeed":36357,"FactionId":0,"Sector":0,"LocationId":0,"BuildingType":19,"Quality":1},{"NameSeed":60955,"FactionId":0,"Sector":0,"LocationId":0,"BuildingType":18,"Quality":4},{"NameSeed":55141,"FactionId":0,"Sector":0,"LocationId":0,"BuildingType":18,"Quality":4},{"NameSeed":56652,"FactionId":0,"Sector":0,"LocationId":0,"BuildingType":18,"Quality":16},{"NameSeed":14015,"FactionId":0,"Sector":0,"LocationId":0,"BuildingType":18,"Quality":14},{"NameSeed":32796,"FactionId":0,"Sector":0,"LocationId":0,"BuildingType":18,"Quality":17},{"NameSeed":54990,"FactionId":0,"Sector":0,"LocationId":0,"BuildingType":18,"Quality":7},{"NameSeed":37482,"FactionId":0,"Sector":0,"LocationId":0,"BuildingType":18,"Quality":12},{"NameSeed":20205,"FactionId":0,"Sector":0,"LocationId":0,"BuildingType":18,"Quality":15},{"NameSeed":53001,"FactionId":0,"Sector":0,"LocationId":0,"BuildingType":18,"Quality":15},{"NameSeed":55568,"FactionId":0,"Sector":0,"LocationId":0,"BuildingType":18,"Quality":17},{"NameSeed":51011,"FactionId":0,"Sector":0,"LocationId":0,"BuildingType":18,"Quality":14},{"NameSeed":3398,"FactionId":0,"Sector":0,"LocationId":0,"BuildingType":18,"Quality":14},{"NameSeed":38158,"FactionId":0,"Sector":0,"LocationId":0,"BuildingType":18,"Quality":6},{"NameSeed":33672,"FactionId":0,"Sector":0,"LocationId":0,"BuildingType":18,"Quality":19},{"NameSeed":57266,"FactionId":0,"Sector":0,"LocationId":0,"BuildingType":18,"Quality":9},{"NameSeed":7480,"FactionId":0,"Sector":0,"LocationId":0,"BuildingType":18,"Quality":10},{"NameSeed":9338,"FactionId":0,"Sector":0,"LocationId":0,"BuildingType":18,"Quality":1},{"NameSeed":28946,"FactionId":0,"Sector":0,"LocationId":0,"BuildingType":19,"Quality":10},{"NameSeed":33676,"FactionId":0,"Sector":0,"LocationId":0,"BuildingType":19,"Quality":12},{"NameSeed":35274,"FactionId":0,"Sector":0,"LocationId":0,"BuildingType":18,"Quality":13},{"NameSeed":3363,"FactionId":0,"Sector":0,"LocationId":0,"BuildingType":21,"Quality":4},{"NameSeed":16278,"FactionId":0,"Sector":0,"LocationId":0,"BuildingType":21,"Quality":14},{"NameSeed":13717,"FactionId":0,"Sector":0,"LocationId":0,"BuildingType":21,"Quality":12},{"NameSeed":58397,"FactionId":0,"Sector":0,"LocationId":0,"BuildingType":21,"Quality":1},{"NameSeed":37246,"FactionId":0,"Sector":0,"LocationId":0,"BuildingType":21,"Quality":6},{"NameSeed":59141,"FactionId":0,"Sector":0,"LocationId":0,"BuildingType":21,"Quality":16},{"NameSeed":45033,"FactionId":0,"Sector":0,"LocationId":0,"BuildingType":21,"Quality":12},{"NameSeed":42776,"FactionId":0,"Sector":0,"LocationId":0,"BuildingType":21,"Quality":7},{"NameSeed":3810,"FactionId":0,"Sector":0,"LocationId":0,"BuildingType":21,"Quality":2},{"NameSeed":35147,"FactionId":0,"Sector":0,"LocationId":0,"BuildingType":21,"Quality":18},{"NameSeed":58232,"FactionId":0,"Sector":0,"LocationId":0,"BuildingType":18,"Quality":5},{"NameSeed":30053,"FactionId":0,"Sector":0,"LocationId":0,"BuildingType":18,"Quality":6},{"NameSeed":3696,"FactionId":0,"Sector":0,"LocationId":0,"BuildingType":18,"Quality":11},{"NameSeed":54146,"FactionId":0,"Sector":0,"LocationId":0,"BuildingType":18,"Quality":16},{"NameSeed":65422,"FactionId":0,"Sector":0,"LocationId":0,"BuildingType":18,"Quality":20},{"NameSeed":47803,"FactionId":0,"Sector":0,"LocationId":0,"BuildingType":18,"Quality":7},{"NameSeed":64326,"FactionId":0,"Sector":0,"LocationId":0,"BuildingType":18,"Quality":4},{"NameSeed":12503,"FactionId":0,"Sector":0,"LocationId":0,"BuildingType":18,"Quality":14},{"NameSeed":12047,"FactionId":236,"Sector":0,"LocationId":0,"BuildingType":2,"Quality":3},{"NameSeed":21765,"FactionId":0,"Sector":0,"LocationId":0,"BuildingType":18,"Quality":5},{"NameSeed":29399,"FactionId":0,"Sector":0,"LocationId":0,"BuildingType":18,"Quality":4},{"NameSeed":1443,"FactionId":0,"Sector":0,"LocationId":0,"BuildingType":18,"Quality":15},{"NameSeed":21878,"FactionId":0,"Sector":0,"LocationId":0,"BuildingType":18,"Quality":10},{"NameSeed":29095,"FactionId":510,"Sector":0,"LocationId":0,"BuildingType":6,"Quality":9},{"NameSeed":48610,"FactionId":0,"Sector":0,"LocationId":0,"BuildingType":18,"Quality":4},{"NameSeed":48815,"FactionId":0,"Sector":0,"LocationId":0,"BuildingType":19,"Quality":5},{"NameSeed":42368,"FactionId":0,"Sector":0,"LocationId":0,"BuildingType":19,"Quality":2},{"NameSeed":5499,"FactionId":0,"Sector":0,"LocationId":0,"BuildingType":18,"Quality":15},{"NameSeed":65162,"FactionId":0,"Sector":0,"LocationId":0,"BuildingType":18,"Quality":2},{"NameSeed":22771,"FactionId":0,"Sector":0,"LocationId":0,"BuildingType":18,"Quality":6},{"NameSeed":37760,"FactionId":0,"Sector":0,"LocationId":0,"BuildingType":18,"Quality":3},{"NameSeed":47726,"FactionId":0,"Sector":0,"LocationId":0,"BuildingType":18,"Quality":9},{"NameSeed":27370,"FactionId":0,"Sector":0,"LocationId":0,"BuildingType":18,"Quality":18},{"NameSeed":2976,"FactionId":0,"Sector":0,"LocationId":0,"BuildingType":18,"Quality":10},{"NameSeed":35321,"FactionId":0,"Sector":0,"LocationId":0,"BuildingType":18,"Quality":6},{"NameSeed":49642,"FactionId":0,"Sector":0,"LocationId":0,"BuildingType":0,"Quality":1},{"NameSeed":12417,"FactionId":0,"Sector":0,"LocationId":0,"BuildingType":18,"Quality":6},{"NameSeed":39598,"FactionId":0,"Sector":0,"LocationId":0,"BuildingType":18,"Quality":16},{"NameSeed":55045,"FactionId":0,"Sector":0,"LocationId":0,"BuildingType":18,"Quality":9},{"NameSeed":12952,"FactionId":0,"Sector":0,"LocationId":0,"BuildingType":18,"Quality":9},{"NameSeed":39650,"FactionId":0,"Sector":0,"LocationId":0,"BuildingType":18,"Quality":4},{"NameSeed":11861,"FactionId":0,"Sector":0,"LocationId":0,"BuildingType":18,"Quality":10},{"NameSeed":61311,"FactionId":0,"Sector":0,"LocationId":0,"BuildingType":18,"Quality":15},{"NameSeed":38413,"FactionId":0,"Sector":0,"LocationId":0,"BuildingType":18,"Quality":10},{"NameSeed":18769,"FactionId":0,"Sector":0,"LocationId":0,"BuildingType":18,"Quality":19},{"NameSeed":958,"FactionId":0,"Sector":0,"LocationId":0,"BuildingType":18,"Quality":18},{"NameSeed":17833,"FactionId":0,"Sector":0,"LocationId":0,"BuildingType":19,"Quality":2},{"NameSeed":38481,"FactionId":0,"Sector":0,"LocationId":0,"BuildingType":18,"Quality":5},{"NameSeed":1803,"FactionId":0,"Sector":0,"LocationId":0,"BuildingType":18,"Quality":6},{"NameSeed":13042,"FactionId":0,"Sector":0,"LocationId":0,"BuildingType":18,"Quality":11},{"NameSeed":5754,"FactionId":0,"Sector":0,"LocationId":0,"BuildingType":18,"Quality":17},{"NameSeed":57879,"FactionId":0,"Sector":0,"LocationId":0,"BuildingType":18,"Quality":13},{"NameSeed":25346,"FactionId":0,"Sector":0,"LocationId":0,"BuildingType":18,"Quality":9},{"NameSeed":57412,"FactionId":0,"Sector":0,"LocationId":0,"BuildingType":18,"Quality":15},{"NameSeed":44581,"FactionId":0,"Sector":0,"LocationId":0,"BuildingType":18,"Quality":1},{"NameSeed":36405,"FactionId":0,"Sector":0,"LocationId":0,"BuildingType":18,"Quality":19},{"NameSeed":13185,"FactionId":0,"Sector":0,"LocationId":0,"BuildingType":18,"Quality":14},{"NameSeed":57918,"FactionId":0,"Sector":0,"LocationId":0,"BuildingType":18,"Quality":13},{"NameSeed":53132,"FactionId":0,"Sector":0,"LocationId":0,"BuildingType":18,"Quality":8},{"NameSeed":17730,"FactionId":0,"Sector":0,"LocationId":0,"BuildingType":18,"Quality":7},{"NameSeed":8257,"FactionId":0,"Sector":0,"LocationId":0,"BuildingType":18,"Quality":15},{"NameSeed":47342,"FactionId":0,"Sector":0,"LocationId":0,"BuildingType":19,"Quality":19},{"NameSeed":39073,"FactionId":0,"Sector":0,"LocationId":0,"BuildingType":19,"Quality":10},{"NameSeed":43565,"FactionId":0,"Sector":0,"LocationId":0,"BuildingType":18,"Quality":3},{"NameSeed":51146,"FactionId":0,"Sector":0,"LocationId":0,"BuildingType":21,"Quality":18},{"NameSeed":56178,"FactionId":0,"Sector":0,"LocationId":0,"BuildingType":21,"Quality":4},{"NameSeed":59394,"FactionId":0,"Sector":0,"LocationId":0,"BuildingType":21,"Quality":13},{"NameSeed":61372,"FactionId":0,"Sector":0,"LocationId":0,"BuildingType":21,"Quality":20}],"ExteriorData":{"AnotherName":"The Shujon Farmstead","MapId":373923,"LocationId":9746,"Width":3,"Height":3,"PortTownAndUnknown":0,"BlockNames":["FARMAA09.RMB","FARMAA07.RMB","FARMAA02.RMB","FARMAA00.RMB","FARMAA09.RMB","FARMAA08.RMB","FARMAA08.RMB","FARMAA00.RMB","FARMAA03.RMB"]}},"Dungeon":{"RecordElement":{"Header":{"X":0,"Y":0,"IsExterior":0,"Unknown2":0,"LocationId":0,"IsInterior":0,"ExteriorLocationId":0,"LocationName":null}},"Header":{"BlockCount":0},"Blocks":null},"Climate":{"WorldClimate":228,"ClimateType":400,"NatureSet":502,"GroundArchive":402,"NatureArchive":502,"SkyBase":24,"People":3,"Names":0},"Politic":51,"RegionIndex":179,"LocationIndex":0}